fixate/__init__.py
fixate/__main__.py
fixate/_switching.py
fixate/main.py
fixate/sequencer.py
fixate/config/__init__.py
fixate/config/helper.py
fixate/core/__init__.py
fixate/core/checks.py
fixate/core/common.py
fixate/core/config_util.py
fixate/core/control.py
fixate/core/exceptions.py
fixate/core/jig_mapping.py
fixate/core/ui.py
fixate/drivers/__init__.py
fixate/drivers/_ftdi.py
fixate/drivers/ftdi.py
fixate/drivers/handlers.py
fixate/drivers/daq/__init__.py
fixate/drivers/daq/daqmx.py
fixate/drivers/dmm/__init__.py
fixate/drivers/dmm/fluke_8846a.py
fixate/drivers/dmm/helper.py
fixate/drivers/dmm/keithley_6500.py
fixate/drivers/dso/__init__.py
fixate/drivers/dso/agilent_mso_x.py
fixate/drivers/dso/helper.py
fixate/drivers/funcgen/__init__.py
fixate/drivers/funcgen/helper.py
fixate/drivers/funcgen/keysight_33500b.py
fixate/drivers/funcgen/rigol_dg1022.py
fixate/drivers/lcr/__init__.py
fixate/drivers/lcr/agilent_u1732c.py
fixate/drivers/lcr/helper.py
fixate/drivers/pps/__init__.py
fixate/drivers/pps/bk_178x.py
fixate/drivers/pps/helper.py
fixate/drivers/pps/siglent_spd_3303X.py
fixate/reporting/__init__.py
fixate/reporting/csv.py
fixate/ui_cmdline/__init__.py
fixate/ui_cmdline/cmd_line.py
fixate/ui_cmdline/kbhit.py
fixate/ui_gui_qt/__init__.py
fixate/ui_gui_qt/layout.py
fixate/ui_gui_qt/subclassed_widgets.py
fixate/ui_gui_qt/ui_gui_qt.py
fixate-0.6.4.dist-info/AUTHORS.txt
fixate-0.6.4.dist-info/LICENSE.txt
fixate-0.6.4.dist-info/METADATA
fixate-0.6.4.dist-info/WHEEL
fixate-0.6.4.dist-info/entry_points.txt
fixate-0.6.4.dist-info/top_level.txt
fixate-0.6.4.dist-info/RECORD
