Metadata-Version: 2.1
Name: fixate
Version: 0.6.4
Summary: Framework for hardware test fixtures and automated test environments
Home-page: http://pyfixate.com/
Author: Ryan Parry-Jones
Author-email: ryanspj+github@gmail.com
Classifier: Development Status :: 4 - Beta
Classifier: Intended Audience :: Manufacturing
Classifier: License :: OSI Approved :: MIT License
Classifier: Operating System :: Microsoft :: Windows
Classifier: Programming Language :: Python :: 3 :: Only
Requires-Python: ~=3.8
License-File: LICENSE.txt
License-File: AUTHORS.txt
Requires-Dist: pyvisa
Requires-Dist: pypubsub
Requires-Dist: pynput
Requires-Dist: ruamel.yaml
Requires-Dist: pyserial
Requires-Dist: cmd2>=2.3.0
Requires-Dist: numpy
Requires-Dist: PyDAQmx
Requires-Dist: platformdirs
Provides-Extra: docs
Requires-Dist: sphinx<8,>=7.4; extra == "docs"
Provides-Extra: gui
Requires-Dist: pyqt5; extra == "gui"
Provides-Extra: test
Requires-Dist: pytest; extra == "test"
Requires-Dist: pytest-mock; extra == "test"
Requires-Dist: pytest-cov; extra == "test"
Requires-Dist: wheel; extra == "test"
